MANIFEST.in
README.rst
requirements.txt
setup.py
corpcrawl/__init__.py
corpcrawl/__init__.pyc
corpcrawl/backend.py
corpcrawl/backend.pyc
corpcrawl/crawler.py
corpcrawl/crawler.pyc
corpcrawl/downloader.py
corpcrawl/downloader.pyc
corpcrawl/parser.py
corpcrawl/parser.pyc
corpcrawl.egg-info/PKG-INFO
corpcrawl.egg-info/SOURCES.txt
corpcrawl.egg-info/dependency_links.txt
corpcrawl.egg-info/top_level.txt
corpcrawl/models/__init__.py
corpcrawl/models/__init__.pyc
corpcrawl/models/models.py
corpcrawl/models/models.pyc
corpcrawl/util/__init__.py
corpcrawl/util/__init__.pyc
corpcrawl/util/cleaner.py
corpcrawl/util/cleaner.pyc
corpcrawl/util/words.py
corpcrawl/util/words.pyc