Metadata-Version: 1.0
Name: corpcrawl
Version: 0.0.34
Summary: Corpcrawl EDGAR Scraper
Home-page: https://github.com/chrisd1891/corpcrawl/
Author: rozap
Author-email: chrisd1891@gmail.com
License: MIT
Platform: any
